{"name":"a002-count","title":"Count","tags":["a","loop"],"description":"Counting is a very important skill in programming.\nCounting from 1 to 10 is easy, but counting for a wide range becomes more difficult.\nYou should write a program to count for you.\n","input":"There are 3 numbers in the input.\nThe first number is the start number.\nThe second number is the end number.\nThe third number is the step number.\n","output":"Your program should output the numbers from the start number to the end number, with the step number.\n","examples":[{"input":"1 5 1\n","output":"1 2 3 4 5\n"},{"input":"1 10 2\n","output":"1 3 5 7 9\n"},{"input":"10 1 -1\n","output":"10 9 8 7 6 5 4 3 2 1\n"}],"subtasks":[{"constraint":"Numbers are in the range of `[1, 1000]`. Step is always `1`.","weight":0.3,"testcases":"./testcases/subtask-1","hash":"be3400f"},{"constraint":"Numbers are in the range of `[-100000, 100000]`.","weight":0.3,"testcases":"./testcases/subtask-2","hash":"3df63db"},{"constraint":"Numbers are in the range of `[-1000000000000, 1000000000000]`.","weight":0.4,"testcases":"./testcases/subtask-3","hash":"d85de12"}],"hint":["`1000000000000` is larger than `2147483647`."],"judge":{"mode":"simple-io"}}